gpteasy/__init__.py
gpteasy/commands.py
gpteasy/display.py
gpteasy/gpt.py
gpteasy/prompts.py
gpteasy/repl.py
gpteasy-1.5.2.dist-info/LICENSE
gpteasy-1.5.2.dist-info/METADATA
gpteasy-1.5.2.dist-info/WHEEL
gpteasy-1.5.2.dist-info/top_level.txt
gpteasy-1.5.2.dist-info/RECORD
