Metadata-Version: 2.1
Name: gpteasy
Version: 1.5.2
Summary: Makes working with OpenAi's GPT API super easy
Author-email: HP Harmsen <hp@harmsen.nl>
License: This is free and unencumbered software released into the public domain.
Project-URL: Homepage, https://github.com/hpharmsen/gpteasy
Keywords: ChatGPT,GPT4,GPT3.5,api
Classifier: Programming Language :: Python
Classifier: Programming Language :: Python :: 3
Requires-Python: >=3.10
License-File: LICENSE
Requires-Dist: openai
Requires-Dist: tenacity
Requires-Dist: python-dateutil
Requires-Dist: python-dotenv
Requires-Dist: rich
Requires-Dist: requests
Requires-Dist: tiktoken
Provides-Extra: dev
Requires-Dist: black ; extra == 'dev'
Requires-Dist: pytest ; extra == 'dev'
Requires-Dist: build ; extra == 'dev'
Requires-Dist: twine ; extra == 'dev'
Requires-Dist: nox ; extra == 'dev'
